push7_cmd/__init__.py
push7_cmd/__version__.py
push7_cmd/cli.py
push7_cmd/exceptions.py
push7_cmd/models.py
push7_cmd-0.0.2.dist-info/DESCRIPTION.rst
push7_cmd-0.0.2.dist-info/METADATA
push7_cmd-0.0.2.dist-info/RECORD
push7_cmd-0.0.2.dist-info/WHEEL
push7_cmd-0.0.2.dist-info/entry_points.txt
push7_cmd-0.0.2.dist-info/metadata.json
push7_cmd-0.0.2.dist-info/top_level.txt
