Metadata-Version: 2.0
Name: push7-cmd
Version: 0.0.2
Summary: easy notification command on terminal using push7
Home-page: https://github.com/a-r-g-v/push7-cmd
Author: Yuki Mukasa
Author-email: info@arg.vc
License: MIT
Platform: UNKNOWN
Classifier: License :: OSI Approved :: MIT License
Classifier: Programming Language :: Python
Classifier: Programming Language :: Python :: 2.6
Classifier: Programming Language :: Python :: 2.7
Classifier: Programming Language :: Python :: 3
Classifier: Programming Language :: Python :: 3.3
Classifier: Programming Language :: Python :: 3.4
Classifier: Programming Language :: Python :: 3.5
Classifier: Programming Language :: Python :: 3.6
Classifier: Programming Language :: Python :: Implementation :: CPython
Classifier: Programming Language :: Python :: Implementation :: PyPy
Requires-Dist: click
Requires-Dist: click-default-group
Requires-Dist: push7
Requires-Dist: six
